tap_neon/__init__.py
tap_neon/__main__.py
tap_neon/client.py
tap_neon/streams.py
tap_neon/tap.py
tap_neon/openapi/__init__.py
tap_neon/openapi/openapi.json
tap_neon-0.5.5.dist-info/METADATA
tap_neon-0.5.5.dist-info/WHEEL
tap_neon-0.5.5.dist-info/entry_points.txt
tap_neon-0.5.5.dist-info/licenses/LICENSE
tap_neon-0.5.5.dist-info/RECORD
