Metadata-Version: 2.4
Name: tap-neon
Version: 0.5.5
Summary: Singer tap for Neon Serverless Postgres, built with the Meltano SDK for Singer Taps.
Project-URL: Documentation, https://github.com/reservoir-data/tap-neon#readme
Project-URL: Homepage, https://github.com/reservoir-data/tap-neon
Project-URL: Source, https://github.com/reservoir-data/tap-neon
Author-email: Edgar Ramírez-Mondragón <edgarrm358@gmail.com>
Maintainer-email: Edgar Ramírez-Mondragón <edgarrm358@gmail.com>
License:                                  Apache License
License-File: LICENSE
Keywords: ELT,Neon Serverless Postgres,singer.io
Classifier: Programming Language :: Python :: 3 :: Only
Classifier: Programming Language :: Python :: 3.10
Classifier: Programming Language :: Python :: 3.11
Classifier: Programming Language :: Python :: 3.12
Classifier: Programming Language :: Python :: 3.13
Classifier: Programming Language :: Python :: 3.14
Requires-Python: >=3.10
Requires-Dist: requests>=2.26
Requires-Dist: singer-sdk~=0.51.0
Requires-Dist: typing-extensions>=4.14.1; python_full_version < '3.12'
